{"ProjectBreakpoints":"{\"Value\":{},\"CodeBreakpoints\":{}}","Compiler":"2","ProjectWatches":"{\"Value\":[]}","OpenedDocuments":"[{\"DocumentPath\":\"Framework/InitAllSettings.xaml\",\"FactoryId\":\"{ACB8E7BA-F093-44C1-9B50-33ECA51AAE16}\"},{\"DocumentPath\":\"Framework/KillAllProcesses.xaml\",\"FactoryId\":\"{ACB8E7BA-F093-44C1-9B50-33ECA51AAE16}\"},{\"DocumentPath\":\"DemoBlaze-OpeningApplications.xaml\",\"FactoryId\":\"{ACB8E7BA-F093-44C1-9B50-33ECA51AAE16}\"},{\"DocumentPath\":\"Framework/InitAllApplications.xaml\",\"FactoryId\":\"{ACB8E7BA-F093-44C1-9B50-33ECA51AAE16}\"},{\"DocumentPath\":\"DemoBlaze-SelectingProducts.xaml\",\"FactoryId\":\"{ACB8E7BA-F093-44C1-9B50-33ECA51AAE16}\"},{\"DocumentPath\":\"Framework/Process.xaml\",\"FactoryId\":\"{ACB8E7BA-F093-44C1-9B50-33ECA51AAE16}\"},{\"DocumentPath\":\"Framework/SetTransactionStatus.xaml\",\"FactoryId\":\"{ACB8E7BA-F093-44C1-9B50-33ECA51AAE16}\"},{\"DocumentPath\":\"Framework/GetTransactionData.xaml\",\"FactoryId\":\"{ACB8E7BA-F093-44C1-9B50-33ECA51AAE16}\"},{\"DocumentPath\":\"DemoBlaze-FetchingTotalAmount.xaml\",\"FactoryId\":\"{ACB8E7BA-F093-44C1-9B50-33ECA51AAE16}\"},{\"DocumentPath\":\"DemoBlaze-SendEmail.xaml\",\"FactoryId\":\"{ACB8E7BA-F093-44C1-9B50-33ECA51AAE16}\"},{\"DocumentPath\":\"Framework/CloseAllApplications.xaml\",\"FactoryId\":\"{ACB8E7BA-F093-44C1-9B50-33ECA51AAE16}\"},{\"DocumentPath\":\"Main.xaml\",\"FactoryId\":\"{ACB8E7BA-F093-44C1-9B50-33ECA51AAE16}\"}]","ProjectActivitiesViewState":"{\"DemoBlaze-SendEmail.xaml\":[{\"ActivityIdRef\":\"SendMailConnections_1\",\"IsAdvancedOptionsExpanded\":false,\"Categories\":{\"Recipients\":true,\"Options\":true},\"Widgets\":{\"To\":{\"ShowExpressionEditor\":false}}}],\"Framework/InitAllApplications.xaml\":[{\"ActivityIdRef\":\"LogMessage_1\",\"IsAdvancedOptionsExpanded\":false,\"Widgets\":{}},{\"ActivityIdRef\":\"InvokeWorkflowFile_1\",\"IsAdvancedOptionsExpanded\":false,\"Categories\":{\"Common\":true,\"Options\":true,\"Log\":true},\"Widgets\":{}}],\"Main.xaml\":[{\"ActivityIdRef\":\"InvokeWorkflowFile_24\",\"IsAdvancedOptionsExpanded\":false,\"Categories\":{\"Common\":true,\"Options\":true,\"Log\":true},\"Widgets\":{}},{\"ActivityIdRef\":\"InvokeWorkflowFile_26\",\"IsAdvancedOptionsExpanded\":false,\"Categories\":{\"Common\":true,\"Options\":true,\"Log\":true},\"Widgets\":{}},{\"ActivityIdRef\":\"LogMessage_32\",\"IsAdvancedOptionsExpanded\":false,\"Widgets\":{}},{\"ActivityIdRef\":\"InvokeWorkflowFile_21\",\"IsAdvancedOptionsExpanded\":false,\"Categories\":{\"Common\":true,\"Options\":true,\"Log\":true},\"Widgets\":{}},{\"ActivityIdRef\":\"LogMessage_31\",\"IsAdvancedOptionsExpanded\":false,\"Widgets\":{}},{\"ActivityIdRef\":\"InvokeWorkflowFile_22\",\"IsAdvancedOptionsExpanded\":false,\"Categories\":{\"Common\":true,\"Options\":true,\"Log\":true},\"Widgets\":{}},{\"ActivityIdRef\":\"InvokeWorkflowFile_33\",\"IsAdvancedOptionsExpanded\":false,\"Categories\":{\"Common\":true,\"Options\":true,\"Log\":true},\"Widgets\":{}},{\"ActivityIdRef\":\"InvokeWorkflowFile_32\",\"IsAdvancedOptionsExpanded\":false,\"Categories\":{\"Common\":true,\"Options\":true,\"Log\":true,\"Output\":true},\"Widgets\":{}}],\"Framework/Process.xaml\":[{\"ActivityIdRef\":\"LogMessage_1\",\"IsAdvancedOptionsExpanded\":false,\"Widgets\":{}},{\"ActivityIdRef\":\"InvokeWorkflowFile_1\",\"IsAdvancedOptionsExpanded\":false,\"Categories\":{\"Common\":true,\"Options\":true,\"Log\":true},\"Widgets\":{}}],\"DemoBlaze-OpeningApplications.xaml\":[{\"ActivityIdRef\":\"LogMessage_1\",\"IsAdvancedOptionsExpanded\":false,\"Widgets\":{}}],\"Framework/InitAllSettings.xaml\":[{\"ActivityIdRef\":\"LogMessage_5\",\"IsAdvancedOptionsExpanded\":false,\"Widgets\":{}},{\"ActivityIdRef\":\"ForEach`1_3\",\"IsAdvancedOptionsExpanded\":false,\"Categories\":{\"\":true},\"Widgets\":{\"Body\":{\"ShowExpanded\":true}}}],\"Framework/KillAllProcesses.xaml\":[{\"ActivityIdRef\":\"LogMessage_1\",\"IsAdvancedOptionsExpanded\":false,\"Widgets\":{}}],\"Framework/GetTransactionData.xaml\":[{\"ActivityIdRef\":\"LogMessage_1\",\"IsAdvancedOptionsExpanded\":false,\"Widgets\":{}}],\"DemoBlaze-SelectingProducts.xaml\":[],\"Framework/CloseAllApplications.xaml\":[{\"ActivityIdRef\":\"LogMessage_1\",\"IsAdvancedOptionsExpanded\":false,\"Widgets\":{}}]}"}